cuda_slic/__init__.py
cuda_slic/slic.py
cuda_slic/types.py
cuda_slic/debug/__init__.py
cuda_slic/debug/__main__.py
cuda_slic/kernels/slic3d_template.cu
gpu_slic-0.0.1a3.dist-info/LICENSE
gpu_slic-0.0.1a3.dist-info/METADATA
gpu_slic-0.0.1a3.dist-info/WHEEL
gpu_slic-0.0.1a3.dist-info/top_level.txt
gpu_slic-0.0.1a3.dist-info/RECORD
