Metadata-Version: 2.1
Name: gpu-slic
Version: 0.0.1a3
Summary: CUDA implementation of the SLIC segmentaion algorithm.
Home-page: https://gitlab.stfc.ac.uk/RosalindFranklinInstitute/cuda-slic
Author: Omar Elamin
Author-email: omar.elamin@diamond.ac.uk
License: UNKNOWN
Keywords: segmentation fast cuda slic clustering kmeans
Platform: UNKNOWN
Classifier: License :: OSI Approved :: Apache Software License
Classifier: Programming Language :: Python :: 3.5
Classifier: Programming Language :: Python :: 3.6
Classifier: Programming Language :: Python :: 3.7
Classifier: Programming Language :: Python :: 3.8
Requires-Python: >=3.6
Requires-Dist: numpy
Requires-Dist: jinja2
Requires-Dist: scikit-image
Requires-Dist: cupy (<8.0.0,>=7.0.0)
